internationalize/__init__.py
internationalize/configure.py
internationalize/provider.py
Internationalize-0.0.2a2.dist-info/LICENSE.md
Internationalize-0.0.2a2.dist-info/METADATA
Internationalize-0.0.2a2.dist-info/WHEEL
Internationalize-0.0.2a2.dist-info/top_level.txt
Internationalize-0.0.2a2.dist-info/RECORD
