Metadata-Version: 2.1
Name: Internationalize
Version: 0.0.2a2
Summary: Helps to internationalize your application
Home-page: https://github.com/piotrmaslanka/internationalize
Author: Piotr Maślanka
Author-email: pmaslanka@smok.co
License: MIT License
Keywords: i18n,internationalize
Platform: posix
Platform: win32
Classifier: Programming Language :: Python
Classifier: Programming Language :: Python :: 2.7
Classifier: Programming Language :: Python :: 3.5
Classifier: Programming Language :: Python :: 3.6
Classifier: Programming Language :: Python :: 3.7
Classifier: Programming Language :: Python :: 3.8
Classifier: Programming Language :: Python :: 3.9
Classifier: Programming Language :: Python :: Implementation :: CPython
Classifier: Programming Language :: Python :: Implementation :: PyPy
Classifier: Operating System :: OS Independent
Classifier: Development Status :: 5 - Production/Stable
Classifier: License :: OSI Approved :: MIT License
Classifier: Topic :: Software Development :: Libraries
Classifier: Intended Audience :: Developers
Classifier: Topic :: Software Development :: Libraries :: Python Modules
Requires-Python: !=2.*,!=3.0.*,!=3.1.*,!=3.2.*,!=3.3.*,!=3.4.*
